BlueWhale3_Educational-0.4.1-py3.8-nspkg.pth
orangecontrib/educational/__init__.py
orangecontrib/educational/i18n_config.py
orangecontrib/educational/locale/educational.en.yml
orangecontrib/educational/locale/educational.zh.yml
orangecontrib/educational/tests/__init__.py
orangecontrib/educational/tutorials/__init__.py
orangecontrib/educational/widgets/__init__.py
orangecontrib/educational/widgets/ow1ka.py
orangecontrib/educational/widgets/owcreatetable.py
orangecontrib/educational/widgets/owgooglesheets.py
orangecontrib/educational/widgets/owgradientdescent.py
orangecontrib/educational/widgets/owkmeans.py
orangecontrib/educational/widgets/owpiecharts.py
orangecontrib/educational/widgets/owpolynomialclassification.py
orangecontrib/educational/widgets/owpolynomialregression.py
orangecontrib/educational/widgets/owrandomdata.py
orangecontrib/educational/widgets/icons/1ka.svg
orangecontrib/educational/widgets/icons/CreateTable.png
orangecontrib/educational/widgets/icons/GoogleSheets.svg
orangecontrib/educational/widgets/icons/GradientDescent.svg
orangecontrib/educational/widgets/icons/InteractiveKMeans.svg
orangecontrib/educational/widgets/icons/PieChart.svg
orangecontrib/educational/widgets/icons/RandomData.svg
orangecontrib/educational/widgets/icons/UnivariateRegression.svg
orangecontrib/educational/widgets/icons/category.svg
orangecontrib/educational/widgets/icons/polynomialclassification.svg
orangecontrib/educational/widgets/tests/__init__.py
orangecontrib/educational/widgets/tests/test_ow1ka.py
orangecontrib/educational/widgets/tests/test_owcreatetable.py
orangecontrib/educational/widgets/tests/test_owgradientdescent.py
orangecontrib/educational/widgets/tests/test_owkmeans.py
orangecontrib/educational/widgets/tests/test_owpiecharts.py
orangecontrib/educational/widgets/tests/test_owpolynomialclassification.py
orangecontrib/educational/widgets/tests/test_owpolynomialregression.py
orangecontrib/educational/widgets/tests/test_owrandomdata.py
BlueWhale3_Educational-0.4.1.dist-info/LICENSE
BlueWhale3_Educational-0.4.1.dist-info/METADATA
BlueWhale3_Educational-0.4.1.dist-info/WHEEL
BlueWhale3_Educational-0.4.1.dist-info/entry_points.txt
BlueWhale3_Educational-0.4.1.dist-info/namespace_packages.txt
BlueWhale3_Educational-0.4.1.dist-info/top_level.txt
BlueWhale3_Educational-0.4.1.dist-info/RECORD
