Metadata-Version: 2.1
Name: BlueWhale3-Educational
Version: 0.4.1
Summary: 用于教学模式的蓝鲸数据挖掘附加组件。
Home-page: https://github.com/biolab/orange3-educational
Author: 大圣实验楼
Author-email: dashenglab@163.com
License: BSD
Download-URL: https://github.com/biolab/orange3-educational/releases
Keywords: orange3 add-on
Platform: UNKNOWN
Requires-Dist: BlueWhale3 (>=3.27.1)
Requires-Dist: BeautifulSoup4
Requires-Dist: numpy
Provides-Extra: doc
Requires-Dist: sphinx ; extra == 'doc'
Requires-Dist: recommonmark ; extra == 'doc'
Requires-Dist: sphinx-rtd-theme ; extra == 'doc'
Provides-Extra: test
Requires-Dist: coverage ; extra == 'test'
